hok/__init__.py
hok/agent.py
hok/battle.py
hok/camp.py
hok/config.dat
hok/config.json
hok/default_hero_config.json
hok/env1v1.py
hok/env1v1_data.py
hok/gamecore_utils.py
hok/server.py
hok/server_delay.py
hok/version.py
hok/lib/interface.cpython-36m-x86_64-linux-gnu.so
hok/lib/interface.cpython-37m-x86_64-linux-gnu.so
hok/lib/interface.cpython-38-x86_64-linux-gnu.so
hok/lib/interface.cpython-39-x86_64-linux-gnu.so
hok/remote_gamecore/remote_launcher.py
hok/unit_test/__init__.py
hok/unit_test/config.json
hok/unit_test/test_env.py
hok_env-1.2.1.dist-info/METADATA
hok_env-1.2.1.dist-info/WHEEL
hok_env-1.2.1.dist-info/top_level.txt
hok_env-1.2.1.dist-info/RECORD
